chatllm/__init__.py
chatllm/chatyuan.py
chatllm/closeai.py
chatllm/embedding.py
chatllm/_his/FaissANN.py
chatllm/_his/__init__.py
chatllm/_his/_chatllm.py
chatllm/_his/_qa.py
chatllm/aigc/__init__.py
chatllm/aigc/common.py
chatllm/api/TODO.md
chatllm/api/__init__.py
chatllm/api/app.py
chatllm/api/config.py
chatllm/api/datamodels.py
chatllm/api/openai_client.py
chatllm/api/sse_api.py
chatllm/api/test.py
chatllm/api/routes/__init__.py
chatllm/api/routes/api.py
chatllm/api/routes/base.py
chatllm/api/routes/completions.py
chatllm/api/routes/embeddings.py
chatllm/api/routes/responses.py
chatllm/applications/Question2Answer.py
chatllm/applications/__chatbase.py
chatllm/applications/__init__.py
chatllm/applications/chatann.py
chatllm/applications/chataudio.py
chatllm/applications/chatbase.py
chatllm/applications/chatcrawler.py
chatllm/applications/chatdoc.py
chatllm/applications/chatmind.py
chatllm/applications/chatpdf.py
chatllm/applications/chatsearch.py
chatllm/applications/chatweb.py
chatllm/applications/chatwhoosh.py
chatllm/applications/pipeline.py
chatllm/clis/README.md
chatllm/clis/__init__.py
chatllm/clis/cli.py
chatllm/llms/__init__.py
chatllm/llms/chatglm.py
chatllm/llms/demo.py
chatllm/llms/llama.py
chatllm/prompts/__init__.py
chatllm/prompts/common.py
chatllm/utils/__init__.py
chatllm/utils/_textsplitter.py
chatllm/utils/common.py
chatllm/utils/gpu_utils.py
chatllm/utils/nbce.py
chatllm/utils/nbce_test.py
chatllm/webui/__init__.py
chatllm/webui/chatbase.py
chatllm/webui/chatpdf.py
chatllm/webui/conf.yaml
chatllm/webui/gradio_ui.py
chatllm/webui/nice_ui.py
chatllm/webui/run.sh
chatllm/webui/visualglm_st.py
llmopenai-2023.6.20.14.24.16.dist-info/LICENSE
llmopenai-2023.6.20.14.24.16.dist-info/METADATA
llmopenai-2023.6.20.14.24.16.dist-info/WHEEL
llmopenai-2023.6.20.14.24.16.dist-info/entry_points.txt
llmopenai-2023.6.20.14.24.16.dist-info/top_level.txt
llmopenai-2023.6.20.14.24.16.dist-info/RECORD
